cv2ext/__init__.py
cv2ext/_flags.py
cv2ext/_jit.py
cv2ext/py.typed
cv2ext/bboxes/__init__.py
cv2ext/bboxes/_algorithms.py
cv2ext/bboxes/_bounding.py
cv2ext/bboxes/_constrain.py
cv2ext/bboxes/_convert.py
cv2ext/bboxes/_distance.py
cv2ext/bboxes/_draw.py
cv2ext/bboxes/_iou.py
cv2ext/bboxes/_mean_ap.py
cv2ext/bboxes/_nms.py
cv2ext/bboxes/_resize.py
cv2ext/bboxes/_score.py
cv2ext/bboxes/_valid.py
cv2ext/cli/__init__.py
cv2ext/cli/annotate/__init__.py
cv2ext/cli/annotate/__main__.py
cv2ext/cli/annotate/_annotate.py
cv2ext/cli/convert_annotations/__init__.py
cv2ext/cli/convert_annotations/__main__.py
cv2ext/cli/convert_annotations/_convert.py
cv2ext/cli/convert_video_color/__init__.py
cv2ext/cli/convert_video_color/__main__.py
cv2ext/cli/convert_video_color/_convert.py
cv2ext/cli/resize_image/__init__.py
cv2ext/cli/resize_image/__main__.py
cv2ext/cli/resize_image/_resize.py
cv2ext/cli/resize_video/__init__.py
cv2ext/cli/resize_video/__main__.py
cv2ext/cli/resize_video/_resize_video.py
cv2ext/cli/timeline/__init__.py
cv2ext/cli/timeline/__main__.py
cv2ext/cli/timeline/_timeline.py
cv2ext/cli/video_from_images/__init__.py
cv2ext/cli/video_from_images/__main__.py
cv2ext/cli/video_from_images/_convert.py
cv2ext/detection/__init__.py
cv2ext/detection/_blob.py
cv2ext/detection/_draw.py
cv2ext/detection/_packer.py
cv2ext/image/__init__.py
cv2ext/image/_augment.py
cv2ext/image/_color.py
cv2ext/image/_divide.py
cv2ext/image/_scale.py
cv2ext/image/_tiling.py
cv2ext/image/color.py
cv2ext/image/draw.py
cv2ext/io/__init__.py
cv2ext/io/_display.py
cv2ext/io/_fourcc.py
cv2ext/io/_iterablevideo.py
cv2ext/io/_webcam.py
cv2ext/io/_writer.py
cv2ext/metrics/__init__.py
cv2ext/metrics/_ncc.py
cv2ext/research/__init__.py
cv2ext/research/biglittle/__init__.py
cv2ext/research/biglittle/_core.py
cv2ext/research/biglittle/_train.py
cv2ext/research/marlin/__init__.py
cv2ext/research/marlin/_change.py
cv2ext/research/marlin/_core.py
cv2ext/research/shift/__init__.py
cv2ext-0.1.1.dist-info/licenses/LICENSE
cv2ext-0.1.1.dist-info/METADATA
cv2ext-0.1.1.dist-info/WHEEL
cv2ext-0.1.1.dist-info/top_level.txt
cv2ext-0.1.1.dist-info/RECORD
