Metadata-Version: 2.4
Name: cv2ext
Version: 0.1.1
Summary: Extended functionality on top of OpenCV
Author-email: Justin Davis <davisjustin302@gmail.com>
Maintainer-email: Justin Davis <davisjustin302@gmail.com>
Project-URL: Homepage, https://github.com/justincdavis/cv2ext
Project-URL: Bug Tracker, https://github.com/justincdavis/cv2ext/issues
Classifier: Development Status :: 4 - Beta
Classifier: Programming Language :: Python :: 3 :: Only
Classifier: Programming Language :: Python :: 3
Classifier: Programming Language :: Python :: 3.8
Classifier: Programming Language :: Python :: 3.9
Classifier: Programming Language :: Python :: 3.10
Classifier: Programming Language :: Python :: 3.11
Classifier: Programming Language :: Python :: 3.12
Classifier: Programming Language :: Python :: 3.13
Classifier: Programming Language :: Python :: Implementation :: CPython
Classifier: License :: OSI Approved :: MIT License
Classifier: Operating System :: Microsoft :: Windows
Classifier: Operating System :: POSIX :: Linux
Classifier: Operating System :: MacOS :: MacOS X
Classifier: Natural Language :: English
Classifier: Intended Audience :: Developers
Classifier: Intended Audience :: Education
Classifier: Intended Audience :: Science/Research
Classifier: Intended Audience :: Education
Classifier: Intended Audience :: End Users/Desktop
Classifier: Typing :: Typed
Requires-Python: <=3.14,>=3.8
License-File: LICENSE
Requires-Dist: opencv-python>=4.8.0
Requires-Dist: numpy<3.0.0,>=1.21.0
Requires-Dist: tqdm>=4.66.0
Requires-Dist: typing_extensions>=4.0.0
Provides-Extra: all
Requires-Dist: cv2ext[jit]; extra == "all"
Requires-Dist: cv2ext[research]; extra == "all"
Provides-Extra: jit
Requires-Dist: numba>=0.55.0; extra == "jit"
Requires-Dist: rocket-fft>=0.2.5; extra == "jit"
Provides-Extra: research
Requires-Dist: cv2ext[marlin]; extra == "research"
Requires-Dist: cv2ext[shift]; extra == "research"
Provides-Extra: marlin
Requires-Dist: joblib; extra == "marlin"
Requires-Dist: scikit-learn; extra == "marlin"
Provides-Extra: shift
Requires-Dist: networkx; extra == "shift"
Provides-Extra: ci
Requires-Dist: ruff<0.10.0,>=0.9.3; extra == "ci"
Requires-Dist: mypy<1.16.0,>=1.14.1; extra == "ci"
Requires-Dist: types-tqdm>=4.66.0; extra == "ci"
Provides-Extra: test
Requires-Dist: pytest>=6.2.0; extra == "test"
Requires-Dist: hypothesis[numpy]>=6.98.0; extra == "test"
Requires-Dist: pybboxes>=0.1.0; extra == "test"
Requires-Dist: opencv-contrib-python>=4.8.0; extra == "test"
Provides-Extra: docs
Requires-Dist: sphinx>=7.0.0; extra == "docs"
Requires-Dist: sphinx_design>=0.6.1; extra == "docs"
Requires-Dist: furo>=2024.8.6; extra == "docs"
Requires-Dist: myst_parser>=3.0.0; extra == "docs"
Provides-Extra: dev
Requires-Dist: cv2ext[jit]; extra == "dev"
Requires-Dist: cv2ext[ci]; extra == "dev"
Requires-Dist: cv2ext[test]; extra == "dev"
Requires-Dist: cv2ext[docs]; extra == "dev"
Requires-Dist: twine>=4.0.0; extra == "dev"
Requires-Dist: wheel>=0.37.0; extra == "dev"
Requires-Dist: bumpver>=2023.1126; extra == "dev"
Requires-Dist: pyclean>=2.7.0; extra == "dev"
Requires-Dist: pyright>=1.1.348; extra == "dev"
Requires-Dist: seaborn>=0.13.0; extra == "dev"
Dynamic: license-file
